__init__.py
__main__.py
arpes_model.py
bandstructure_model.py
dos_model.py
input_parser.py
library.py
octopost.py
output_read_model.py
units.py
Octopost-1.0.0.post1.dist-info/LICENSE.txt
Octopost-1.0.0.post1.dist-info/METADATA
Octopost-1.0.0.post1.dist-info/WHEEL
Octopost-1.0.0.post1.dist-info/top_level.txt
Octopost-1.0.0.post1.dist-info/RECORD
