Metadata-Version: 2.1
Name: Octopost
Version: 1.0.0.post1
Summary: Octopost contains a pool of python3 tools for post-processing data obtained with the TDDFT code OCTOPUS.
Home-page: https://gitlab.com/ckern/octopost
Author: Christian Kern, MSc.
Author-email: christian.kern@uni-graz.at
License: UNKNOWN
Platform: UNKNOWN
Classifier: Topic :: Documentation :: Sphinx
Classifier: Natural Language :: English
Classifier: Operating System :: POSIX :: Linux
Classifier: Programming Language :: Python
Classifier: Programming Language :: Python :: 3
Classifier: Programming Language :: Python :: 3.8
Classifier: Topic :: Communications :: Email
Classifier: Topic :: Scientific/Engineering :: Physics
Classifier: Topic :: Software Development :: Version Control :: Git
Classifier: Topic :: Text Processing :: Markup :: reStructuredText
Classifier: License :: OSI Approved :: MIT License
Requires-Python: >=3.8
License-File: LICENSE.txt
Requires-Dist: numpy (>=1.20)
Requires-Dist: scipy (>=1.5)
Requires-Dist: vtk (>=9.0)
Requires-Dist: matplotlib (>=3.3)
Requires-Dist: h5py (>=3.0)
Provides-Extra: dev
Requires-Dist: sphinx (==4.1.2) ; extra == 'dev'
Requires-Dist: check-manifest (==0.46) ; extra == 'dev'
Requires-Dist: twine (==3.4.2) ; extra == 'dev'
Requires-Dist: sphinx-rtd-theme (==0.5.2) ; extra == 'dev'
Provides-Extra: docs
Requires-Dist: sphinx (==4.1.2) ; extra == 'docs'
Requires-Dist: sphinx-rtd-theme (==0.5.2) ; extra == 'docs'
Provides-Extra: test
Requires-Dist: pytest (==6.2.5) ; extra == 'test'
Requires-Dist: flake8 (==3.9.2) ; extra == 'test'
